SFC_TF/Fmodel.py
SFC_TF/VERSION
SFC_TF/__init__.py
SFC_TF/mask.py
SFC_TF/packingscore.py
SFC_TF/patterson.py
SFC_TF/symmetry.py
SFC_TF/utils.py
SFC_TF/voxel.py
tests/__init__.py
tests/conftest.py
tests/test_Fmodel.py
tests/test_voxel.py
SFcalculator_tf-0.1.5.dist-info/METADATA
SFcalculator_tf-0.1.5.dist-info/WHEEL
SFcalculator_tf-0.1.5.dist-info/top_level.txt
SFcalculator_tf-0.1.5.dist-info/RECORD
