Metadata-Version: 2.1
Name: SFcalculator-tf
Version: 0.1.5
Summary: A Differentiable pipeline connecting molecule models and crystallpgraphy data
Home-page: https://github.com/Hekstra-Lab/SFcalculator
Author: Minhaun Li
Author-email: minhuanli@g.harvard.edu
License: MIT
Platform: UNKNOWN
Requires-Python: >=3.7
Requires-Dist: gemmi (>=0.5.6)
Requires-Dist: reciprocalspaceship (>=0.9.18)
Requires-Dist: tensorflow (>=2.6.0)
Requires-Dist: tensorflow-probability (>=0.14.0)
